Metadata-Version: 1.1
Name: Python-Deprecated
Version: 1.0.0
Summary: Python Deprecated Decorator
Home-page: https://github.com/vrcmarcos/python-deprecated
Author: Marcos Cardoso
Author-email: vrcmarcos@gmail.com
License: MIT
Platform: any
Classifier: Environment :: Web Environment
Classifier: Intended Audience :: Developers
Classifier: Operating System :: OS Independent
Classifier: Programming Language :: Python
Classifier: Topic :: Software Development :: Libraries :: Python Modules
